gitexcely/__init__.py
gitexcely/cli.py
gitexcely/helpers.py
gitexcely/log.py
gitexcely/main.py
gitexcely/py_git.py
gitexcely/excel_convert/__init__.py
gitexcely/excel_convert/generate_excel.py
gitexcely/excel_convert/parsing_excel.py
gitexcely-1.0.dist-info/LICENSE
gitexcely-1.0.dist-info/METADATA
gitexcely-1.0.dist-info/WHEEL
gitexcely-1.0.dist-info/entry_points.txt
gitexcely-1.0.dist-info/top_level.txt
gitexcely-1.0.dist-info/RECORD
