Metadata-Version: 2.1
Name: gitexcely
Version: 1.0
Summary: Python CLI tool with Git for MS Excel version control using text
Home-page: https://github.com/hellofromtheothersky/Excel-data-version-control-via-Git
Author: Hieu Nguyen Hung Trung
License: Apache License, Version 2.0
License-File: LICENSE
Requires-Dist: openpyxl ==3.1.5
Requires-Dist: pandas ==2.2.2
Requires-Dist: setuptools ==70.2.0
Requires-Dist: XlsxWriter ==3.2.0
